mypack1337/__init__.py
mypack1337-0.0.2.dist-info/METADATA
mypack1337-0.0.2.dist-info/WHEEL
mypack1337-0.0.2.dist-info/top_level.txt
mypack1337-0.0.2.dist-info/RECORD
